README.rst
setup.py
cloudy/__init__.py
cloudy/cloudy.py
cloudy.egg-info/PKG-INFO
cloudy.egg-info/SOURCES.txt
cloudy.egg-info/dependency_links.txt
cloudy.egg-info/not-zip-safe
cloudy.egg-info/requires.txt
cloudy.egg-info/top_level.txt