Metadata-Version: 1.1
Name: cloudy
Version: 0.1.0
Summary: cloudy parses cloudy output files to pandas Data Frames
Home-page: https://github.com/pbvarga1/cloudy
Author: Perry Vargas
Author-email: perrybvargas@gmail.com
License: BSD
Keywords: cloudy
Platform: UNKNOWN
Classifier: License :: OSI Approved :: BSD License
Classifier: Natural Language :: English
Classifier: Programming Language :: Python :: 2
Classifier: Programming Language :: Python :: 2.6
Classifier: Programming Language :: Python :: 2.7
Classifier: Programming Language :: Python :: 3
Classifier: Programming Language :: Python :: 3.3
Classifier: Programming Language :: Python :: 3.4
